mlbench_lite/__init__.py
mlbench_lite/benchmark.py
mlbench_lite/datasets.py
mlbench_lite-2.0.3.dist-info/licenses/LICENSE
mlbench_lite-2.0.3.dist-info/METADATA
mlbench_lite-2.0.3.dist-info/WHEEL
mlbench_lite-2.0.3.dist-info/entry_points.txt
mlbench_lite-2.0.3.dist-info/top_level.txt
mlbench_lite-2.0.3.dist-info/RECORD
